README.md
setup.py
decoProf/__init__.py
decoProf/core.py
decoProf/decoProf.py
decoProf/genericProfiler.py
decoProf/info.py
decoProf/io_manager.py
decoProf.egg-info/PKG-INFO
decoProf.egg-info/SOURCES.txt
decoProf.egg-info/dependency_links.txt
decoProf.egg-info/entry_points.txt
decoProf.egg-info/requires.txt
decoProf.egg-info/top_level.txt