Metadata-Version: 2.1
Name: decoProf
Version: 0.0.1
Summary: Profiler aggregator
Home-page: https://github.com/maxim-masterov/decoProf
Author: Maxim Masterov
Author-email: maksim.masterov@surf.nl
License: MIT
Platform: UNKNOWN
